Metadata-Version: 2.1
Name: pycheops-ultra
Version: 1.0.4
Summary: CHEOPS light curve analysis software
Home-page: http://cheops.unibe.ch/
Author: CHEOPS Science Team
Author-email: p.maxted@keele.ac.uk
License: GNU GPLv3
Keywords: astronomy
Platform: UNKNOWN
Classifier: Development Status :: 1 - Planning
Classifier: Intended Audience :: Science/Research
Classifier: Topic :: Scientific/Engineering
Classifier: License :: OSI Approved :: GNU General Public License v3 (GPLv3)
Classifier: Programming Language :: Python :: 3.6
License-File: LICENSE
Requires-Dist: numpy (>=1.17.2)
Requires-Dist: pyyaml (>=5.3)
Requires-Dist: scipy
Requires-Dist: astropy (>=3.2.2)
Requires-Dist: emcee (>=3.0.0)
Requires-Dist: astroquery
Requires-Dist: numba (>=0.44.1)
Requires-Dist: lmfit (>=0.9.14)
Requires-Dist: corner
Requires-Dist: photutils
Requires-Dist: matplotlib (>3.2)
Requires-Dist: celerite2
Requires-Dist: cdspyreadme
Requires-Dist: python-dace-client (>2.0.0)
Requires-Dist: tqdm
Requires-Dist: ipython (>=7.30.1)
Requires-Dist: ultranest (>=3.3.0)
Requires-Dist: cython (>=0.29.24)
Requires-Dist: pathos (>=0.2.8)
Requires-Dist: mpi4py (>=3.0.0)
Requires-Dist: scikit-learn (>=0.24.2)
Requires-Dist: statsmodels (>=0.12.2)
Requires-Dist: cryptography (>=36.0.0)
Requires-Dist: h5py (>=3.5.0)
Requires-Dist: selenium (>=3.141.0)
